{
    "Productos": [
        {
            "Marca": "DELLTechnologies",
            "Nombre": "Dell Latitude 9450 2-in-1 U7 165U",
            "SistemaOperativo": "Version S.O. Windows 11 Pro",
            "Procesador": {
                "Familia": "Intel Core Ultra 7",
                "Modelo": "164U",
                "Fabricante": "Intel",
                "Frecuencia": "4,4 GHZ",
                "Núcleos": ""
            },
            "RAM": {
                "Instalada": "32 GB",
                "Máxima": "32 GB",
                "BancosLibres": "0",
                "Velocidad": "7.467 MHZ",
                "Tecnología": "DDR5"
            },
            "DiscoDuro": {
                "Capacidad": "1.024 GB",
                "Tipo": "SSD",
                "Interfaz": "PCI Express 4.0",
                "NúmeroSoportes": "1",
                "Velocidad": ""
            },
            "TarjetaGrafica": {
                "Integrada": "No",
                "Fabricante": "Intel",
                "Modelo": "UHD Graphics",
                "Memoria": "0 mb"
            },
            "DimensionesPeso": {
                "Peso": "1,54 kg",
                "Altura": "1,28 cm",
                "Ancho": "31,1 cm",
                "Profundidad": "2,15 cm"
            },
            "Codigo": "GN4X0",
            "Precio": "2.542,61 €",
            "Pantalla": {
                "Tamaño": "14\"",
                "Táctil": "Si",
                "Tipo": "TFT",
                "Resolución": "2560 x 1600",
                "Superficie": "",
                "Luminosidad": "",
                "Contraste": "",
                "TiempoRefresco": ""
            },
            "General": {
                "Color": "Gris",
                "TPM": "No",
                "MaterialChasis": "",
                "DetecciónHuella": "",
                "Convertibilidad": ""
            },
            "Conexiones": {
                "ConexiónRedMóvil": "Si",
                "NºPuertosUSB": "",
                "PuertosUSB": "",
                "Ethernet": "Ethernet 10/100/1000",
                "Bluetooth": {
                    "Disponible": "Si",
                    "Versión": ""
                },
                "PuertoThunderbolt": "Si",
                "PuertoHDMI": "No",
                "OtrasConexiones": "Porte VGA No"
            },
            "Audio": {
                "MicrófonoIntegrado": "Si",
                "Altavoces": ""
            },
            "Bateria": {
                "NúmeroCeldas": "3",
                "Duración": "",
                "Capacidad": ""
            },
            "Webcam": {
                "Integrada": "Si",
                "Resolución": "",
                "Infrarrojos": ""
            },
            "Teclado": {
                "Numérico": "",
                "Retroiluminado": "",
                "NúmeroTeclas": ""
            }
        }
    ]
}